Metadata-Version: 2.4
Name: django_mentor_myenglishkr
Version: 5.1.8
Summary: Demiansoft template(mentor)
Requires-Python: >=3.6
Requires-Dist: Django>=4.2.11
Requires-Dist: shared_lib_ds>=1.3.7
Requires-Dist: libsass
Requires-Dist: django-sass-processor
Requires-Dist: django-compressor
